imutils2/__init__.py
imutils2/core.py
imutils2/merge.py
imutils2-0.3.5.dist-info/LICENSE
imutils2-0.3.5.dist-info/METADATA
imutils2-0.3.5.dist-info/WHEEL
imutils2-0.3.5.dist-info/RECORD
