Metadata-Version: 2.1
Name: imutils2
Version: 0.3.5
Summary: image utils
Home-page: https://github.com/codeskyblue/imutils2
License: MIT
Author: Sully
Author-email: codeskyblue@gmail.com
Requires-Python: >=3.8,<4.0
Classifier: License :: OSI Approved :: MIT License
Classifier: Programming Language :: Python :: 3
Classifier: Programming Language :: Python :: 3.8
Classifier: Programming Language :: Python :: 3.9
Classifier: Programming Language :: Python :: 3.10
Classifier: Programming Language :: Python :: 3.11
Classifier: Programming Language :: Python :: 3.12
Provides-Extra: opencv
Requires-Dist: Pillow
Requires-Dist: numpy
Requires-Dist: opencv-python ; extra == "opencv"
Requires-Dist: requests
Requires-Dist: typeguard
